chrisrichardmiles/__init__.py
chrisrichardmiles/_modidx.py
chrisrichardmiles/_nbdev.py
chrisrichardmiles/core.py
chrisrichardmiles/m5/__init__.py
chrisrichardmiles/m5/daily_models.py
chrisrichardmiles/m5/fe.py
chrisrichardmiles/m5/metric.py
chrisrichardmiles/m5/oos.py
chrisrichardmiles-0.0.5.dist-info/LICENSE
chrisrichardmiles-0.0.5.dist-info/METADATA
chrisrichardmiles-0.0.5.dist-info/WHEEL
chrisrichardmiles-0.0.5.dist-info/entry_points.txt
chrisrichardmiles-0.0.5.dist-info/top_level.txt
chrisrichardmiles-0.0.5.dist-info/RECORD
